elrpy/dgp.py
elrpy/losses.py
elrpy/models.py
elrpy/optim.py
elrpy/utils.py
elrpy/data/data.py
elrpy/data/np_utils.py
elrpy/data/pd_utils.py
elrpy/data/utils.py
elrpy/inference/bootstrap.py
elrpy/inference/normal.py
elrpy-0.0.5.dist-info/LICENSE
elrpy-0.0.5.dist-info/METADATA
elrpy-0.0.5.dist-info/WHEEL
elrpy-0.0.5.dist-info/top_level.txt
elrpy-0.0.5.dist-info/RECORD
