Metadata-Version: 2.1
Name: elrpy
Version: 0.0.5
Summary: A lightweight package for individual level inference in elections backed by jax.
Author-email: Nic Fishman <njwfish@gmail.com>
Project-URL: Homepage, https://github.com/DataforProgress/elrpy/
Project-URL: Bug Tracker, https://github.com/DataforProgress/elrpy/tree/issues
Classifier: Programming Language :: Python :: 3
Classifier: License :: OSI Approved :: MIT License
Classifier: Operating System :: OS Independent
Requires-Python: >=3.8
License-File: LICENSE
Requires-Dist: pandas
Requires-Dist: numpy
Requires-Dist: jax
Requires-Dist: jaxlib
